src/rom.v
module rom(input wire [7:0] addr,output reg [7:0] data_out);

    reg [7:0] rom_mem [0:255];
    integer i;  

    initial begin
        rom_mem[0] = 8'hAA;
        rom_mem[1] = 8'hFF;
        rom_mem[2] = 8'hF4;
        rom_mem[3] = 8'hB2;
        rom_mem[4] = 8'hE0;
        rom_mem[5] = 8'hD3;
        rom_mem[6] = 8'hF1;
        rom_mem[7] = 8'hB6;
        rom_mem[8] = 8'hA3;
        for (i = 9; i < 256; i = i + 1) begin
            rom_mem[i] = 8'h00;
        end
    end

    always @(*) begin
        data_out = rom_mem[addr];
    end

endmodule

src/rom_tb.v
`timescale 1ns/1ps
`include "rom.v"

module tb_rom;

    reg [7:0] addr;
    wire [7:0] data_out;

    rom rom_inst (
        .addr(addr),
        .data_out(data_out)
    );

    initial begin
        $dumpfile("rom.vcd");
        $dumpvars(0, tb_rom);
        
        addr = 0;
        #10;
        $display("Tiempo: %0t | Direccion: %0d | Dato leido: %h", $time, addr, data_out);

        addr = 1;
        #10;
        $display("Tiempo: %0t | Direccion: %0d | Dato leido: %h", $time, addr, data_out);

        addr = 2;
        #5;
        $display("Tiempo: %0t | Direccion: %0d | Dato leido: %h", $time, addr, data_out);
        
        addr = 3;
        #5;
        $display("Tiempo: %0t | Direccion: %0d | Dato leido: %h", $time, addr, data_out);

        addr = 4;
        #10;
        $display("Tiempo: %0t | Direccion: %0d | Dato leido: %h", $time, addr, data_out);

        addr = 5;
        #5;
        $display("Tiempo: %0t | Direccion: %0d | Dato leido: %h", $time, addr, data_out);

        addr = 6;
        #5;
        $display("Tiempo: %0t | Direccion: %0d | Dato leido: %h", $time, addr, data_out);

        addr = 7;
        #5;
        $display("Tiempo: %0t | Direccion: %0d | Dato leido: %h", $time, addr, data_out);

        addr = 8;
        #5;
        $display("Tiempo: %0t | Direccion: %0d | Dato leido: %h", $time, addr, data_out);

        #10;
        $finish;  
    end

endmodule

src/rom.vcd
$date
	Wed Aug 27 18:16:40 2025
$end
$version
	Icarus Verilog
$end
$timescale
	1ps
$end
$scope module tb_rom $end
$var wire 8 ! data_out [7:0] $end
$var reg 8 " addr [7:0] $end
$scope module rom_inst $end
$var wire 8 # addr [7:0] $end
$var reg 8 $ data_out [7:0] $end
$var integer 32 % i [31:0] $end
$upscope $end
$upscope $end
$enddefinitions $end
$comment Show the parameter values. $end
$dumpall
$end
#0
$dumpvars
b100000000 %
b10101010 $
b0 #
b0 "
b10101010 !
$end
#10000
b11111111 !
b11111111 $
b1 "
b1 #
#20000
b11110100 !
b11110100 $
b10 "
b10 #
#25000
b10110010 !
b10110010 $
b11 "
b11 #
#30000
b11100000 !
b11100000 $
b100 "
b100 #
#40000
b11010011 !
b11010011 $
b101 "
b101 #
#45000
b11110001 !
b11110001 $
b110 "
b110 #
#50000
b10110110 !
b10110110 $
b111 "
b111 #
#55000
b10100011 !
b10100011 $
b1000 "
b1000 #
